answer/__init__.py
answer/answer_pb2.py
answer/answer_pb2_grpc.py
answer_generated-0.1.0.dist-info/METADATA
answer_generated-0.1.0.dist-info/WHEEL
answer_generated-0.1.0.dist-info/top_level.txt
answer_generated-0.1.0.dist-info/RECORD
