Metadata-Version: 2.1
Name: answer_generated
Version: 0.1.0
Summary: Generated Python files for answer service
Home-page: https://github.com/danyatalent/protos
Author: Danya Talent
Author-email: Danya Talent <danyatalent@mail.ru>
License: MIT
Project-URL: Homepage, https://github.com/danyatalent/protos
Requires-Python: >=3.6
Requires-Dist: grpcio
Requires-Dist: protobuf
